cardlib/__init__.py
cardlib/card.py
cardlib/deck.py
cardlib/dice.py
cardlib-1.1.0.dist-info/licenses/LICENSE
cardlib-1.1.0.dist-info/METADATA
cardlib-1.1.0.dist-info/WHEEL
cardlib-1.1.0.dist-info/top_level.txt
cardlib-1.1.0.dist-info/RECORD
