Metadata-Version: 2.4
Name: cardlib
Version: 1.1.0
Summary: Reusable card and dice library for text-based games
Author-email: Jeffrey Ray <jeffrey.ray@bell.net>
License: MIT
Project-URL: Homepage, https://github.com/jray-8/cardlib
Project-URL: Repository, https://github.com/jray-8/cardlib
Classifier: Programming Language :: Python :: 3
Classifier: License :: OSI Approved :: MIT License
Classifier: Operating System :: OS Independent
Classifier: Intended Audience :: Developers
Classifier: Topic :: Games/Entertainment
Requires-Python: >=3.8
License-File: LICENSE
Dynamic: license-file
